djamazing
