Metadata-Version: 1.1
Name: djamazing
Version: 0.1.0
Summary: Safe storage for django using AWS S3+CloudFront
Home-page: https://github.com/sunscrapers/djamazing
Author: SUNSCRAPERS
Author-email: info@sunscrapers.com
License: MIT
Platform: UNKNOWN
Classifier: Development Status :: 4 - Beta
Classifier: Environment :: Web Environment
Classifier: Framework :: Django :: 1.8
Classifier: Framework :: Django :: 1.9
Classifier: Framework :: Django :: 1.10
Classifier: Intended Audience :: Developers
Classifier: License :: OSI Approved :: MIT License
Classifier: Programming Language :: Python :: 2.7
Classifier: Programming Language :: Python :: 3.4
Classifier: Programming Language :: Python :: 3.5
Classifier: Programming Language :: Python :: 3.6
Classifier: Topic :: Communications :: File Sharing
